{
  "Sierpinski\u4e09\u89d2\u5f62 gen=4 (Phase 0)": {
    "label": "Sierpinski\u4e09\u89d2\u5f62 gen=4 (Phase 0)",
    "N": 42,
    "N_bank_0": 6,
    "eps_c": 0.43000000000000005,
    "scan": [
      {
        "eps": 0.0,
        "N_bank": 6,
        "ratio": 1.0
      },
      {
        "eps": 0.02,
        "N_bank": 6,
        "ratio": 1.0
      },
      {
        "eps": 0.04,
        "N_bank": 6,
        "ratio": 1.0
      },
      {
        "eps": 0.06,
        "N_bank": 6,
        "ratio": 1.0
      },
      {
        "eps": 0.08,
        "N_bank": 6,
        "ratio": 1.0
      },
      {
        "eps": 0.1,
        "N_bank": 6,
        "ratio": 1.0
      },
      {
        "eps": 0.12000000000000001,
        "N_bank": 6,
        "ratio": 1.0
      },
      {
        "eps": 0.13999999999999999,
        "N_bank": 6,
        "ratio": 1.0
      },
      {
        "eps": 0.16,
        "N_bank": 5,
        "ratio": 0.8333333333333334
      },
      {
        "eps": 0.18,
        "N_bank": 5,
        "ratio": 0.8333333333333334
      },
      {
        "eps": 0.19999999999999998,
        "N_bank": 5,
        "ratio": 0.8333333333333334
      },
      {
        "eps": 0.22,
        "N_bank": 5,
        "ratio": 0.8333333333333334
      },
      {
        "eps": 0.24,
        "N_bank": 5,
        "ratio": 0.8333333333333334
      },
      {
        "eps": 0.26,
        "N_bank": 5,
        "ratio": 0.8333333333333334
      },
      {
        "eps": 0.28,
        "N_bank": 4,
        "ratio": 0.6666666666666666
      },
      {
        "eps": 0.30000000000000004,
        "N_bank": 4,
        "ratio": 0.6666666666666666
      },
      {
        "eps": 0.32,
        "N_bank": 4,
        "ratio": 0.6666666666666666
      },
      {
        "eps": 0.34,
        "N_bank": 4,
        "ratio": 0.6666666666666666
      },
      {
        "eps": 0.36000000000000004,
        "N_bank": 4,
        "ratio": 0.6666666666666666
      },
      {
        "eps": 0.38,
        "N_bank": 4,
        "ratio": 0.6666666666666666
      },
      {
        "eps": 0.4,
        "N_bank": 4,
        "ratio": 0.6666666666666666
      },
      {
        "eps": 0.42000000000000004,
        "N_bank": 4,
        "ratio": 0.6666666666666666
      },
      {
        "eps": 0.44,
        "N_bank": 3,
        "ratio": 0.5
      },
      {
        "eps": 0.46,
        "N_bank": 3,
        "ratio": 0.5
      },
      {
        "eps": 0.48000000000000004,
        "N_bank": 3,
        "ratio": 0.5
      },
      {
        "eps": 0.5,
        "N_bank": 3,
        "ratio": 0.5
      }
    ],
    "percolation_exponent": {
      "beta": 0.15181844226956756,
      "log_A": 1.8686734015037174
    }
  },
  "Vicsek\u30d5\u30e9\u30af\u30bf\u30eb gen=3 (Phase 1)": {
    "label": "Vicsek\u30d5\u30e9\u30af\u30bf\u30eb gen=3 (Phase 1)",
    "N": 125,
    "N_bank_0": 18,
    "eps_c": 0.33,
    "scan": [
      {
        "eps": 0.0,
        "N_bank": 18,
        "ratio": 1.0
      },
      {
        "eps": 0.02,
        "N_bank": 18,
        "ratio": 1.0
      },
      {
        "eps": 0.04,
        "N_bank": 18,
        "ratio": 1.0
      },
      {
        "eps": 0.06,
        "N_bank": 18,
        "ratio": 1.0
      },
      {
        "eps": 0.08,
        "N_bank": 18,
        "ratio": 1.0
      },
      {
        "eps": 0.1,
        "N_bank": 18,
        "ratio": 1.0
      },
      {
        "eps": 0.12000000000000001,
        "N_bank": 18,
        "ratio": 1.0
      },
      {
        "eps": 0.13999999999999999,
        "N_bank": 18,
        "ratio": 1.0
      },
      {
        "eps": 0.16,
        "N_bank": 18,
        "ratio": 1.0
      },
      {
        "eps": 0.18,
        "N_bank": 15,
        "ratio": 0.8333333333333334
      },
      {
        "eps": 0.19999999999999998,
        "N_bank": 15,
        "ratio": 0.8333333333333334
      },
      {
        "eps": 0.22,
        "N_bank": 15,
        "ratio": 0.8333333333333334
      },
      {
        "eps": 0.24,
        "N_bank": 15,
        "ratio": 0.8333333333333334
      },
      {
        "eps": 0.26,
        "N_bank": 13,
        "ratio": 0.7222222222222222
      },
      {
        "eps": 0.28,
        "N_bank": 10,
        "ratio": 0.5555555555555556
      },
      {
        "eps": 0.30000000000000004,
        "N_bank": 10,
        "ratio": 0.5555555555555556
      },
      {
        "eps": 0.32,
        "N_bank": 10,
        "ratio": 0.5555555555555556
      },
      {
        "eps": 0.34,
        "N_bank": 8,
        "ratio": 0.4444444444444444
      },
      {
        "eps": 0.36000000000000004,
        "N_bank": 8,
        "ratio": 0.4444444444444444
      },
      {
        "eps": 0.38,
        "N_bank": 7,
        "ratio": 0.3888888888888889
      },
      {
        "eps": 0.4,
        "N_bank": 7,
        "ratio": 0.3888888888888889
      },
      {
        "eps": 0.42000000000000004,
        "N_bank": 7,
        "ratio": 0.3888888888888889
      },
      {
        "eps": 0.44,
        "N_bank": 7,
        "ratio": 0.3888888888888889
      },
      {
        "eps": 0.46,
        "N_bank": 6,
        "ratio": 0.3333333333333333
      },
      {
        "eps": 0.48000000000000004,
        "N_bank": 5,
        "ratio": 0.2777777777777778
      },
      {
        "eps": 0.5,
        "N_bank": 5,
        "ratio": 0.2777777777777778
      }
    ],
    "percolation_exponent": {
      "beta": 0.22194369798433117,
      "log_A": 3.1814890158645315
    }
  },
  "\u30e9\u30f3\u30c0\u30e0\u70b9\u7fa4 N=60 (Phase 3)": {
    "label": "\u30e9\u30f3\u30c0\u30e0\u70b9\u7fa4 N=60 (Phase 3)",
    "N": 60,
    "N_bank_0": 3359,
    "eps_c": 0.03,
    "scan": [
      {
        "eps": 0.0,
        "N_bank": 3359,
        "ratio": 1.0
      },
      {
        "eps": 0.02,
        "N_bank": 2265,
        "ratio": 0.6743078297112236
      },
      {
        "eps": 0.04,
        "N_bank": 869,
        "ratio": 0.258707948794284
      },
      {
        "eps": 0.06,
        "N_bank": 363,
        "ratio": 0.10806787734444775
      },
      {
        "eps": 0.08,
        "N_bank": 192,
        "ratio": 0.05715986900863352
      },
      {
        "eps": 0.1,
        "N_bank": 117,
        "ratio": 0.034831795177136055
      },
      {
        "eps": 0.12000000000000001,
        "N_bank": 75,
        "ratio": 0.02232807383149747
      },
      {
        "eps": 0.13999999999999999,
        "N_bank": 56,
        "ratio": 0.016671628460851445
      },
      {
        "eps": 0.16,
        "N_bank": 41,
        "ratio": 0.01220601369455195
      },
      {
        "eps": 0.18,
        "N_bank": 34,
        "ratio": 0.01012206013694552
      },
      {
        "eps": 0.19999999999999998,
        "N_bank": 26,
        "ratio": 0.007740398928252456
      },
      {
        "eps": 0.22,
        "N_bank": 19,
        "ratio": 0.0056564453706460256
      },
      {
        "eps": 0.24,
        "N_bank": 16,
        "ratio": 0.004763322417386127
      },
      {
        "eps": 0.26,
        "N_bank": 14,
        "ratio": 0.004167907115212861
      },
      {
        "eps": 0.28,
        "N_bank": 15,
        "ratio": 0.004465614766299494
      },
      {
        "eps": 0.30000000000000004,
        "N_bank": 11,
        "ratio": 0.003274784161952962
      },
      {
        "eps": 0.32,
        "N_bank": 11,
        "ratio": 0.003274784161952962
      },
      {
        "eps": 0.34,
        "N_bank": 10,
        "ratio": 0.002977076510866329
      },
      {
        "eps": 0.36000000000000004,
        "N_bank": 10,
        "ratio": 0.002977076510866329
      },
      {
        "eps": 0.38,
        "N_bank": 7,
        "ratio": 0.0020839535576064306
      },
      {
        "eps": 0.4,
        "N_bank": 7,
        "ratio": 0.0020839535576064306
      },
      {
        "eps": 0.42000000000000004,
        "N_bank": 7,
        "ratio": 0.0020839535576064306
      },
      {
        "eps": 0.44,
        "N_bank": 6,
        "ratio": 0.0017862459065197975
      },
      {
        "eps": 0.46,
        "N_bank": 6,
        "ratio": 0.0017862459065197975
      },
      {
        "eps": 0.48000000000000004,
        "N_bank": 5,
        "ratio": 0.0014885382554331646
      },
      {
        "eps": 0.5,
        "N_bank": 5,
        "ratio": 0.0014885382554331646
      }
    ]
  }
}